dbt_osmosis/__init__.py
dbt_osmosis/__main__.py
dbt_osmosis/cli/__init__.py
dbt_osmosis/cli/main.py
dbt_osmosis/core/__init__.py
dbt_osmosis/core/llm.py
dbt_osmosis/core/logger.py
dbt_osmosis/core/osmosis.py
dbt_osmosis/sql/proxy.py
dbt_osmosis/workbench/app.py
dbt_osmosis/workbench/requirements.txt
dbt_osmosis/workbench/components/dashboard.py
dbt_osmosis/workbench/components/editor.py
dbt_osmosis/workbench/components/feed.py
dbt_osmosis/workbench/components/preview.py
dbt_osmosis/workbench/components/profiler.py
dbt_osmosis/workbench/components/renderer.py
dbt_osmosis-1.1.17.dist-info/METADATA
dbt_osmosis-1.1.17.dist-info/WHEEL
dbt_osmosis-1.1.17.dist-info/entry_points.txt
dbt_osmosis-1.1.17.dist-info/licenses/LICENSE
dbt_osmosis-1.1.17.dist-info/RECORD
