Metadata-Version: 2.3
Name: dbt-osmosis
Version: 1.1.17
Summary: A dbt utility for managing YAML to make developing with dbt more delightful.
Author-email: z3z1ma <butler.alex2010@gmail.com>
License: Apache-2.0
Keywords: dbt,osmosis,yaml
Classifier: Development Status :: 4 - Beta
Classifier: Intended Audience :: Developers
Classifier: License :: OSI Approved :: Apache Software License
Classifier: Programming Language :: Python :: 3.9
Classifier: Programming Language :: Python :: 3.10
Classifier: Programming Language :: Python :: 3.11
Classifier: Programming Language :: Python :: 3.12
Classifier: Topic :: Software Development :: Build Tools
Requires-Python: <3.13,>=3.9
Requires-Dist: click<9,>7
Requires-Dist: dbt-core<=1.10,>=1.8
Requires-Dist: mysql-mimic>=2.5.7
Requires-Dist: pluggy<2,>=1.5.0
Requires-Dist: rich>=10
Requires-Dist: ruamel-yaml<0.19,>=0.17
Requires-Dist: typing-extensions~=4.13.1; python_version < '3.10'
Provides-Extra: dev
Requires-Dist: dbt-duckdb<2,>=1.0.0; extra == 'dev'
Requires-Dist: pre-commit<5,>3.0.0; extra == 'dev'
Requires-Dist: pytest~=8.3.4; extra == 'dev'
Requires-Dist: ruff~=0.8.4; extra == 'dev'
Provides-Extra: openai
Requires-Dist: openai~=1.58.1; extra == 'openai'
Provides-Extra: workbench
Requires-Dist: dbt-duckdb<=1.10,>=1.8.0; extra == 'workbench'
Requires-Dist: feedparser~=6.0.11; extra == 'workbench'
Requires-Dist: setuptools>=70; extra == 'workbench'
Requires-Dist: streamlit-ace~=0.1.1; extra == 'workbench'
Requires-Dist: streamlit-elements-fluence>=0.1.4; extra == 'workbench'
Requires-Dist: streamlit<1.34.0,>=1.20.0; extra == 'workbench'
Requires-Dist: ydata-profiling~=4.12.1; extra == 'workbench'
